pyqode.qt-2.10.0-py3.5-nspkg.pth
pyqode/qt/QtCore.py
pyqode/qt/QtDesigner.py
pyqode/qt/QtGui.py
pyqode/qt/QtNetwork.py
pyqode/qt/QtTest.py
pyqode/qt/QtWebWidgets.py
pyqode/qt/QtWidgets.py
pyqode/qt/__init__.py
pyqode.qt-2.10.0.dist-info/DESCRIPTION.rst
pyqode.qt-2.10.0.dist-info/METADATA
pyqode.qt-2.10.0.dist-info/RECORD
pyqode.qt-2.10.0.dist-info/WHEEL
pyqode.qt-2.10.0.dist-info/metadata.json
pyqode.qt-2.10.0.dist-info/namespace_packages.txt
pyqode.qt-2.10.0.dist-info/top_level.txt
