Metadata-Version: 1.1
Name: pyqode.qt
Version: 2.10.0
Summary: Shim library that wraps PyQt5, PyQt4 and PySide
Home-page: https://github.com/pyQode/pyqode.qt
Author: Colin Duquesnoy
Author-email: colin.duquesnoy@gmail.com
License: MIT
Keywords: qt PyQt4 PyQt5 PySide
Platform: UNKNOWN
Classifier: Development Status :: 5 - Production/Stable
Classifier: Environment :: X11 Applications :: Qt
Classifier: Environment :: Win32 (MS Windows)
Classifier: Intended Audience :: Developers
Classifier: License :: OSI Approved :: MIT License
Classifier: Operating System :: Microsoft :: Windows
Classifier: Operating System :: POSIX :: Linux
Classifier: Programming Language :: Python :: 2.7
Classifier: Programming Language :: Python :: 3.2
Classifier: Programming Language :: Python :: 3.3
Classifier: Programming Language :: Python :: 3.4
Classifier: Topic :: Software Development :: Widget Sets
